{
  "name": "File Output (Testing)",
  "description": "Output to file for testing purposes",
  "input": {
    "type": "hls",
    "source": "https://cdn.itassist.one/BREAKING/NEWS/index.m3u8",
    "params": ""
  },
  "output": {
    "type": "file",
    "source": "/tmp/test_output.ts",
    "params": ""
  },
  "tsduck_command": "tsp -I hls https://cdn.itassist.one/BREAKING/NEWS/index.m3u8 -O file /tmp/test_output.ts",
  "service": {
    "service_name": "SCTE-35 Stream",
    "provider_name": "ITAssist",
    "service_id": 1,
    "vpid": 256,
    "apid": 257,
    "scte35_pid": 500,
    "null_pid": 8191,
    "pcr_pid": 256
  },
  "scte35": {
    "ad_duration": 600,
    "event_id": 100023,
    "preroll_duration": 0,
    "pmt_enabled": true,
    "pmt_params": "",
    "spliceinject_enabled": true,
    "spliceinject_params": ""
  }
}